[
{"w":"込み上げる","r":"こみあげる","m":"trào dâng lên trong lòng","jp":"感情が内から湧き上がる","ex":"卒業生の背中を見て、込み上げるものがあった。","exvi":"Nhìn tấm lưng lũ học trò tốt nghiệp, có gì đó trào dâng trong lòng."},
{"w":"張り詰める","r":"はりつめる","m":"căng như dây đàn","jp":"緊張が極度に高まる","ex":"本番を前に、神経が張り詰める。","exvi":"Trước giờ diễn chính thức, thần kinh căng như dây đàn."},
{"w":"立ち込める","r":"たちこめる","m":"bao trùm giăng kín","jp":"煙や霧が辺りを覆う","ex":"朝霧が立ち込める田んぼは、まだ夢の続きのようだ。","exvi":"Cánh đồng lúa sương sớm giăng kín trông như giấc mơ còn dang dở."},
{"w":"かみ砕く","r":"かみくだく","m":"diễn giải cho dễ hiểu","jp":"分かりやすく説明する","ex":"難しい話をかみ砕く力は、深く理解した証だ","exvi":"Khả năng diễn giải điều khó hiểu ra là bằng chứng đã hiểu sâu."},
{"w":"打ち込む","r":"うちこむ","m":"lao đầu dốc sức vào","jp":"熱中して取り組む","ex":"何かに打ち込む横顔は、年齢を消す。","exvi":"Gương mặt nghiêng khi dốc sức vào việc gì đó xóa nhòa tuổi tác."},
{"w":"食い下がる","r":"くいさがる","m":"bám riết không buông","jp":"粘り強く追及する","ex":"食い下がる新人の質問が、古い前提を崩した。","exvi":"Câu hỏi bám riết của lính mới làm sụp một tiền đề cũ kỹ."},
{"w":"見逃す","r":"みのがす","m":"bỏ sót, làm ngơ cho qua","jp":"気づかず見過ごす","ex":"小さな成長を見逃すと、信頼を一つ失う。","exvi":"Bỏ sót một tiến bộ nhỏ là đánh mất một phần niềm tin."},
{"w":"見計らう","r":"みはからう","m":"canh chừng thời điểm","jp":"ちょうどよい頃合いを判断する","ex":"部屋を出るタイミングを見計らう。","exvi":"Canh chừng đúng thời điểm để rời khỏi phòng."},
{"w":"はにかむ","r":"はにかむ","m":"e thẹn ngượng ngùng","jp":"恥ずかしそうにする","ex":"褒められてはにかむ職人の手は、止まらない。","exvi":"Người thợ e thẹn khi được khen, nhưng đôi tay vẫn không ngừng."},
{"w":"たじろぐ","r":"たじろぐ","m":"chùn lại nao núng","jp":"気おされてひるむ","ex":"相手の勢いにたじろぐな、深呼吸を一つ。","exvi":"Đừng chùn trước khí thế đối phương, hãy hít một hơi thật sâu."},
{"w":"うろつく","r":"うろつく","m":"lảng vảng loanh quanh","jp":"あてもなく歩き回る","ex":"締め切り前ほど、冷蔵庫の前をうろつく。","exvi":"Càng gần hạn chót càng hay lảng vảng trước tủ lạnh."},
{"w":"へりくだる","r":"へりくだる","m":"hạ mình khiêm nhường","jp":"自分を低くして接する","ex":"過度にへりくだる必要はない、対等でいい。","exvi":"Không cần hạ mình thái quá, cứ ngang hàng là được."},
{"w":"かしこまる","r":"かしこまる","m":"cung kính giữ lễ; ngồi ngay ngắn","jp":"礼儀正しく畏まる","ex":"式では誰もがかしこまるが、宴では緩む。","exvi":"Ở buổi lễ ai cũng cung kính giữ lễ, nhưng vào tiệc thì thả lỏng."},
{"w":"あくせく","r":"あくせく","m":"tất bật lam lũ vì miếng cơm","jp":"せかせか働き詰めるさま","ex":"あくせく稼ぐ月より、静かに整える月が要る。","exvi":"Cần cả những tháng lặng lẽ sắp xếp, chứ không chỉ tháng tất bật kiếm tiền."},
{"w":"じわじわ","r":"じわじわ","m":"ngấm dần từ từ","jp":"少しずつ確実に進む","ex":"良い本は、じわじわ効いてくる。","exvi":"Sách hay ngấm từ từ."},
{"w":"ふわっと","r":"ふわっと","m":"nhẹ bẫng phồng lên","jp":"軽く柔らかく浮くさま","ex":"焼きたてのパンが、ふわっと湯気を上げる。","exvi":"Ổ bánh mì vừa ra lò bốc hơi nhẹ bẫng."},
{"w":"ぎゅっと","r":"ぎゅっと","m":"siết chặt dồn nén","jp":"強く握り締めるさま","ex":"不安な夜は、枕をぎゅっと抱えて眠る。","exvi":"Đêm bất an, ôm ghì cái gối mà ngủ."},
{"w":"ぽつぽつ","r":"ぽつぽつ","m":"lác đác lẻ tẻ","jp":"少しずつまばらに","ex":"ぽつぽつ集まった客が、いつの間にか満席になる。","exvi":"Khách lác đác kéo tới, chẳng mấy chốc kín chỗ."},
{"w":"ずるずる","r":"ずるずる","m":"lằng nhằng kéo dài dây dưa","jp":"決着せず長引くさま","ex":"ずるずる続く会議は、椅子を片づけると終わる。","exvi":"Cuộc họp dây dưa lê thê sẽ kết thúc khi dọn ghế đi."},
{"w":"こそこそ","r":"こそこそ","m":"lén lút giấu giếm","jp":"人目を避けてひそかに","ex":"こそこそ食べるお菓子が、一番おいしい。","exvi":"Món bánh ăn lén là món ngon nhất."},
{"w":"陽炎","r":"かげろう","m":"ảo ảnh nắng rung trên đường","jp":"熱で空気が揺れて見える現象","ex":"夏の道に立つ陽炎は、遠い記憶を歪ませる。","exvi":"Ảo ảnh nắng rung trên con đường mùa hạ làm méo cả ký ức xa xăm."},
{"w":"木漏れ日","r":"こもれび","m":"nắng lọt qua kẽ lá","jp":"葉の間から差す日の光","ex":"木漏れ日の下の昼寝は、どんな高級寝具にも勝つ。","exvi":"Giấc trưa dưới nắng lọt kẽ lá thắng mọi loại chăn đệm cao cấp."},
{"w":"夕凪","r":"ゆうなぎ","m":"khoảng lặng gió lúc chiều tà","jp":"夕方に風がやむこと","ex":"夕凪の海は、一日の疲れを黙って受け止める。","exvi":"Biển lặng gió chiều tà lặng lẽ đón lấy mệt mỏi một ngày."},
{"w":"名残惜しい","r":"なごりおしい","m":"bịn rịn lưu luyến","jp":"別れがつらく心残り","ex":"名残惜しい別れほど、次の再会が濃くなる。","exvi":"Cuộc chia tay càng bịn rịn thì lần gặp lại càng đậm đà."},
{"w":"清らか","r":"きよらか","m":"trong trẻo thanh khiết","jp":"汚れなく澄んださま","ex":"清らかな湧き水は、一口で言葉を減らす。","exvi":"Ngụm nước nguồn trong trẻo khiến người ta bớt lời đi."},
{"w":"儚い","r":"はかない","m":"phù du mong manh","jp":"消えやすくもろい","ex":"儚い桜だから、人はカメラより目に焼き付ける。","exvi":"Vì hoa anh đào phù du nên người ta khắc vào mắt hơn là vào máy ảnh."},
{"w":"麗しい","r":"うるわしい","m":"đẹp đẽ tao nhã","jp":"美しく気高い","ex":"麗しい友情は、貸し借りを数えない。","exvi":"Tình bạn đẹp đẽ không đếm nợ vay qua lại."},
{"w":"奥ゆかしい","r":"おくゆかしい","m":"kín đáo mà đằm thắm cuốn hút","jp":"上品で慎み深い","ex":"奥ゆかしい看板の店ほど、料理が雄弁だ。","exvi":"Quán có tấm biển càng kín đáo thì món ăn càng hùng hồn."},
{"w":"清廉","r":"せいれん","m":"thanh liêm trong sạch","jp":"心が清く欲がない","ex":"清廉さは、誰も見ていない領収書に表れる。","exvi":"Sự thanh liêm hiện ra ở tấm hóa đơn không ai nhìn tới."},
{"w":"寛容","r":"かんよう","m":"khoan dung độ lượng","jp":"心が広く受け入れる","ex":"寛容は弱さではなく、鍛えられた強さだ。","exvi":"Khoan dung không phải yếu đuối mà là sức mạnh đã tôi luyện."},
{"w":"寛大","r":"かんだい","m":"rộng lượng bao dung","jp":"心が広く咎めない","ex":"他人に寛大で、自分に厳しいのが理想だが、逆が多い。","exvi":"Lý tưởng là rộng lượng với người, khắt khe với mình — nhưng đời hay ngược lại."},
{"w":"篤実","r":"とくじつ","m":"trung hậu chân thành","jp":"情に厚く誠実な","ex":"篤実な人柄は、契約書より仕事を運ぶ。","exvi":"Tính cách trung hậu mang việc về nhiều hơn cả hợp đồng."},
{"w":"実直","r":"じっちょく","m":"thật thà ngay thẳng","jp":"正直でまじめな","ex":"実直な仕事は地味だが、二度目の注文を連れてくる。","exvi":"Làm ăn thật thà tuy tẻ nhạt nhưng kéo về đơn hàng lần hai."},
{"w":"温厚","r":"おんこう","m":"ôn hòa hiền hậu","jp":"穏やかで優しい","ex":"温厚な人が本気で怒る時、皆が姿勢を正す。","exvi":"Khi người ôn hòa thật sự nổi giận, ai nấy đều ngồi thẳng lại."},
{"w":"円熟","r":"えんじゅく","m":"chín muồi lão luyện","jp":"経験を積んで熟達した","ex":"円熟した芸は、力を抜く勇気から生まれる。","exvi":"Ngón nghề chín muồi sinh ra từ cái gan dám buông sức."},
{"w":"老練","r":"ろうれん","m":"lão luyện dày dạn","jp":"経験豊かで巧み","ex":"老練な船長は、嵐より先に船員の顔色を読む。","exvi":"Thuyền trưởng dày dạn đọc sắc mặt thủy thủ trước cả cơn bão."},
{"w":"熟達","r":"じゅくたつ","m":"tinh thông thành thạo","jp":"よく慣れて上達すること","ex":"熟達への近道は、退屈な反復を面白がることだ。","exvi":"Đường tắt tới tinh thông là biết thấy vui trong sự lặp lại tẻ nhạt."},
{"w":"精進","r":"しょうじん","m":"tinh tấn dốc lòng rèn luyện","jp":"一心に努め励むこと","ex":"日々の精進は、結果が出ない日にこそ効いている。","exvi":"Sự tinh tấn mỗi ngày phát huy tác dụng chính vào những ngày chưa có kết quả."},
{"w":"研鑽","r":"けんさん","m":"dày công trau dồi","jp":"学問や技を深く磨くこと","ex":"研鑽を積む人は、質問の質でわかる。","exvi":"Người dày công trau dồi lộ ra qua chất lượng câu hỏi."},
{"w":"鍛錬","r":"たんれん","m":"tôi luyện rèn giũa","jp":"心身を鍛えること","ex":"鍛錬は裏切らないが、すぐには返事をくれない。","exvi":"Tôi luyện không phản bội, chỉ là chẳng trả lời ngay."},
{"w":"賜杯","r":"しはい","m":"cúp do bậc tôn quý trao tặng","jp":"貴人から授かる優勝杯","ex":"賜杯を掲げる腕より、震える膝が真実を語る。","exvi":"Đôi đầu gối run rẩy nói lên sự thật nhiều hơn cánh tay nâng cúp."},
{"w":"面目躍如","r":"めんもくやくじょ","m":"nở mày nở mặt đúng danh tiếng","jp":"評価通りの活躍をするさま","ex":"土壇場の一手に、名人の面目躍如たるものがある。","exvi":"Nước cờ phút chót đúng là làm rạng danh bậc kỳ thủ."},
{"w":"面食らう","r":"めんくらう","m":"ngớ người bối rối","jp":"突然のことに戸惑う","ex":"急な指名に面食らうと、準備した言葉が飛ぶ。","exvi":"Ngớ người vì bị gọi tên đột ngột thì bao lời soạn sẵn bay hết."},
{"w":"気後れ","r":"きおくれ","m":"nhụt chí e dè trước đám đông","jp":"気持ちがひるむこと","ex":"立派な会場に気後れするな、話す中身は変わらない。","exvi":"Đừng nhụt chí vì hội trường sang trọng — nội dung nói vẫn thế."},
{"w":"気転","r":"きてん","m":"nhanh trí ứng biến","jp":"その場に応じた機敏な判断","ex":"気転の利く一言が、凍った空気を溶かす。","exvi":"Một câu nhanh trí làm tan bầu không khí đóng băng."},
{"w":"機微","r":"きび","m":"cái tế nhị khó nắm bắt của lòng người","jp":"微妙な心の動き","ex":"人の心の機微は、マニュアルに載っていない。","exvi":"Cái tế nhị trong lòng người không có trong cẩm nang."},
{"w":"含蓄","r":"がんちく","m":"hàm súc sâu xa","jp":"深い意味が込もっていること","ex":"含蓄のある短い言葉は、長い演説に勝つ。","exvi":"Câu ngắn hàm súc thắng bài diễn văn dài."},
{"w":"風格","r":"ふうかく","m":"phong thái khí độ","jp":"備わった品格・威厳","ex":"風格は服では買えず、選んだ苦労から滲む。","exvi":"Phong thái không mua bằng áo quần, nó rịn ra từ những gian khó đã chọn."},
{"w":"気概","r":"きがい","m":"khí phách chí khí","jp":"困難に立ち向かう強い意志","ex":"気概のある辞退は、無責任な承諾に勝る。","exvi":"Lời từ chối đầy khí phách hơn hẳn cái gật đầu vô trách nhiệm."},
{"w":"矜持","r":"きょうじ","m":"lòng tự tôn nghề nghiệp","jp":"自分の誇り","ex":"職人の矜持は、見えない裏側の仕上げに宿る。","exvi":"Lòng tự tôn của người thợ ngụ ở phần hoàn thiện khuất mắt."},
{"w":"気骨","r":"きこつ","m":"cốt cách cứng cỏi không khuất phục","jp":"信念を曲げない強さ","ex":"気骨のある部下は、上司を育てる。","exvi":"Người cấp dưới có cốt cách cứng cỏi lại rèn giũa cấp trên."},
{"w":"素地","r":"そじ","m":"cái nền có sẵn để phát triển","jp":"基礎となる下地","ex":"信頼の素地があれば、多少の失敗は流れる。","exvi":"Có sẵn cái nền tin cậy thì đôi ba cú vấp cũng trôi qua."},
{"w":"下地","r":"したじ","m":"lớp nền lót; nền tảng","jp":"物事の基礎・準備","ex":"読書の下地がある子は、どの教科でも伸びる。","exvi":"Đứa trẻ có nền đọc sách thì môn nào cũng tiến."},
{"w":"礎","r":"いしずえ","m":"nền móng đặt nền","jp":"物事を支える基礎","ex":"無名の年月が、後の名声の礎になる。","exvi":"Những năm tháng vô danh trở thành nền móng cho danh tiếng về sau."},
{"w":"骨子","r":"こっし","m":"bộ khung ý chính","jp":"物事の中心となる要点","ex":"提案の骨子は、封筒の裏に三行で書ける。","exvi":"Khung ý chính của đề xuất viết gọn ba dòng sau lưng phong bì."},
{"w":"要諦","r":"ようてい","m":"điểm mấu chốt cốt yếu","jp":"最も大切な点","ex":"接客の要諦は、売ることより覚えることだ。","exvi":"Mấu chốt của tiếp khách là ghi nhớ, hơn là bán hàng."},
{"w":"真っ向","r":"まっこう","m":"chính diện đối đầu thẳng","jp":"正面から向き合うさま","ex":"批判に真っ向から答える潔さが、場を静める。","exvi":"Sự đường hoàng đối mặt thẳng với chỉ trích làm cả phòng lặng đi."},
{"w":"如才ない","r":"じょさいない","m":"khéo léo chu toàn không sơ suất","jp":"気が利いて抜け目ない","ex":"如才ない対応の裏に、地道な下調べがある。","exvi":"Sau cách ứng xử khéo léo chu toàn là sự tìm hiểu cần mẫn."},
{"w":"抜け目ない","r":"ぬけめない","m":"tinh ranh không hớ hênh chỗ nào","jp":"手抜かりがなくずる賢い","ex":"抜け目ない人ほど、礼儀という保険を欠かさない。","exvi":"Người tinh ranh càng không quên khoản bảo hiểm mang tên lễ nghĩa."},
{"w":"そつがない","r":"そつがない","m":"đâu ra đấy không tì vết","jp":"手落ちや無駄がない","ex":"そつがない仕事は安心だが、心に残るのは少し欠けた方だ。","exvi":"Việc làm đâu ra đấy thì yên tâm, nhưng thứ đọng lại trong tim là thứ hơi khiếm khuyết."}
]
